dm_mac/__init__.py
dm_mac/cli_utils.py
dm_mac/models/__init__.py
dm_mac/models/machine.py
dm_mac/models/users.py
dm_mac/neon_fob_adder.py
dm_mac/neongetter.py
dm_mac/py.typed
dm_mac/slack_handler.py
dm_mac/utils.py
dm_mac/views/__init__.py
dm_mac/views/api.py
dm_mac/views/machine.py
dm_mac/views/prometheus.py
machine_access_control-0.8.0.dist-info/METADATA
machine_access_control-0.8.0.dist-info/WHEEL
machine_access_control-0.8.0.dist-info/entry_points.txt
machine_access_control-0.8.0.dist-info/licenses/LICENSE
machine_access_control-0.8.0.dist-info/RECORD
