Metadata-Version: 2.4
Name: machine_access_control
Version: 0.8.0
Summary: Decatur Makers Machine Access Control package
License: MIT
License-File: LICENSE
Author: Jason Antman
Author-email: jason@jasonantman.com
Requires-Python: >=3.12,<4.0
Classifier: Development Status :: 3 - Alpha
Classifier: License :: OSI Approved :: MIT License
Classifier: Programming Language :: Python :: 3
Classifier: Programming Language :: Python :: 3.12
Classifier: Programming Language :: Python :: 3.13
Classifier: Programming Language :: Python :: 3.14
Requires-Dist: aiohttp (>=3.12.14,<4.0.0)
Requires-Dist: asyncio (>=3.4.3,<4.0.0)
Requires-Dist: filelock (>=3.20.1,<4.0.0)
Requires-Dist: humanize (>=4.11.0,<5.0.0)
Requires-Dist: jsonschema (>=4.23.0,<5.0.0)
Requires-Dist: marshmallow (>=4.1.2,<5.0.0)
Requires-Dist: prometheus-client (>=0.20.0,<0.21.0)
Requires-Dist: quart (>=0.20.0,<0.21.0)
Requires-Dist: requests (>=2.32.4,<3.0.0)
Requires-Dist: slack-bolt (>=1.21.3,<2.0.0)
Requires-Dist: slack-sdk (>=3.33.5,<4.0.0)
Requires-Dist: urllib3 (>=2.6.0,<3.0.0)
Requires-Dist: werkzeug (>=3.1.4,<4.0.0)
Project-URL: Changelog, https://github.com/jantman/machine_access_control/releases
Project-URL: Documentation, https://github.com/jantman/machine_access_control
Project-URL: Homepage, https://github.com/jantman/machine_access_control
Project-URL: Repository, https://github.com/jantman/machine_access_control
